[{"iob":-0.637,"activity":-0.0001,"bolussnooze":0,"basaliob":-0.637,"netbasalinsulin":-0.4,"hightempinsulin":0.4,"time":"2017-02-05T09:00:36.000Z"},{"iob":-0.732,"activity":-0.0009,"bolussnooze":0,"basaliob":-0.732,"netbasalinsulin":-0.5,"hightempinsulin":0.4,"time":"2017-02-05T09:05:36.000Z"},{"iob":-0.823,"activity":-0.0018,"bolussnooze":0,"basaliob":-0.823,"netbasalinsulin":-0.6,"hightempinsulin":0.4,"time":"2017-02-05T09:10:36.000Z"},{"iob":-0.859,"activity":-0.0028,"bolussnooze":0,"basaliob":-0.859,"netbasalinsulin":-0.65,"hightempinsulin":0.4,"time":"2017-02-05T09:15:36.000Z"},{"iob":-0.94,"activity":-0.0038,"bolussnooze":0,"basaliob":-0.94,"netbasalinsulin":-0.75,"hightempinsulin":0.4,"time":"2017-02-05T09:20:36.000Z"},{"iob":-0.916,"activity":-0.0049,"bolussnooze":0,"basaliob":-0.916,"netbasalinsulin":-0.75,"hightempinsulin":0.4,"time":"2017-02-05T09:25:36.000Z"},{"iob":-0.886,"activity":-0.0058,"bolussnooze":0,"basaliob":-0.886,"netbasalinsulin":-0.75,"hightempinsulin":0.4,"time":"2017-02-05T09:30:36.000Z"},{"iob":-0.853,"activity":-0.0067,"bolussnooze":0,"basaliob":-0.853,"netbasalinsulin":-0.75,"hightempinsulin":0.4,"time":"2017-02-05T09:35:36.000Z"},{"iob":-0.815,"activity":-0.0075,"bolussnooze":0,"basaliob":-0.815,"netbasalinsulin":-0.75,"hightempinsulin":0.4,"time":"2017-02-05T09:40:36.000Z"},{"iob":-0.774,"activity":-0.0082,"bolussnooze":0,"basaliob":-0.774,"netbasalinsulin":-0.75,"hightempinsulin":0.4,"time":"2017-02-05T09:45:36.000Z"},{"iob":-0.73,"activity":-0.0088,"bolussnooze":0,"basaliob":-0.73,"netbasalinsulin":-0.75,"hightempinsulin":0.4,"time":"2017-02-05T09:50:36.000Z"},{"iob":-0.683,"activity":-0.0093,"bolussnooze":0,"basaliob":-0.683,"netbasalinsulin":-0.8,"hightempinsulin":0.35,"time":"2017-02-05T09:55:36.000Z"},{"iob":-0.635,"activity":-0.0096,"bolussnooze":0,"basaliob":-0.635,"netbasalinsulin":-0.85,"hightempinsulin":0.3,"time":"2017-02-05T10:00:36.000Z"},{"iob":-0.586,"activity":-0.0099,"bolussnooze":0,"basaliob":-0.586,"netbasalinsulin":-0.9,"hightempinsulin":0.25,"time":"2017-02-05T10:05:36.000Z"},{"iob":-0.536,"activity":-0.01,"bolussnooze":0,"basaliob":-0.536,"netbasalinsulin":-0.95,"hightempinsulin":0.2,"time":"2017-02-05T10:10:36.000Z"},{"iob":-0.486,"activity":-0.0099,"bolussnooze":0,"basaliob":-0.486,"netbasalinsulin":-1,"hightempinsulin":0.15,"time":"2017-02-05T10:15:36.000Z"},{"iob":-0.437,"activity":-0.0098,"bolussnooze":0,"basaliob":-0.437,"netbasalinsulin":-1.05,"hightempinsulin":0.1,"time":"2017-02-05T10:20:36.000Z"},{"iob":-0.39,"activity":-0.0095,"bolussnooze":0,"basaliob":-0.39,"netbasalinsulin":-1.1,"hightempinsulin":0.05,"time":"2017-02-05T10:25:36.000Z"},{"iob":-0.345,"activity":-0.009,"bolussnooze":0,"basaliob":-0.345,"netbasalinsulin":-1.15,"hightempinsulin":0,"time":"2017-02-05T10:30:36.000Z"},{"iob":-0.302,"activity":-0.0085,"bolussnooze":0,"basaliob":-0.302,"netbasalinsulin":-1.15,"hightempinsulin":0,"time":"2017-02-05T10:35:36.000Z"},{"iob":-0.263,"activity":-0.0079,"bolussnooze":0,"basaliob":-0.263,"netbasalinsulin":-1.15,"hightempinsulin":0,"time":"2017-02-05T10:40:36.000Z"},{"iob":-0.226,"activity":-0.0073,"bolussnooze":0,"basaliob":-0.226,"netbasalinsulin":-1.15,"hightempinsulin":0,"time":"2017-02-05T10:45:36.000Z"},{"iob":-0.193,"activity":-0.0067,"bolussnooze":0,"basaliob":-0.193,"netbasalinsulin":-1.15,"hightempinsulin":0,"time":"2017-02-05T10:50:36.000Z"},{"iob":-0.163,"activity":-0.0061,"bolussnooze":0,"basaliob":-0.163,"netbasalinsulin":-1.15,"hightempinsulin":0,"time":"2017-02-05T10:55:36.000Z"},{"iob":-0.135,"activity":-0.0055,"bolussnooze":0,"basaliob":-0.135,"netbasalinsulin":-1.15,"hightempinsulin":0,"time":"2017-02-05T11:00:36.000Z"},{"iob":-0.111,"activity":-0.0048,"bolussnooze":0,"basaliob":-0.111,"netbasalinsulin":-1.15,"hightempinsulin":0,"time":"2017-02-05T11:05:36.000Z"},{"iob":-0.09,"activity":-0.0043,"bolussnooze":0,"basaliob":-0.09,"netbasalinsulin":-1.1,"hightempinsulin":0,"time":"2017-02-05T11:10:36.000Z"},{"iob":-0.071,"activity":-0.0037,"bolussnooze":0,"basaliob":-0.071,"netbasalinsulin":-1.05,"hightempinsulin":0,"time":"2017-02-05T11:15:36.000Z"},{"iob":-0.056,"activity":-0.0031,"bolussnooze":0,"basaliob":-0.056,"netbasalinsulin":-1,"hightempinsulin":0,"time":"2017-02-05T11:20:36.000Z"},{"iob":-0.042,"activity":-0.0027,"bolussnooze":0,"basaliob":-0.042,"netbasalinsulin":-0.9,"hightempinsulin":0,"time":"2017-02-05T11:25:36.000Z"},{"iob":-0.031,"activity":-0.0022,"bolussnooze":0,"basaliob":-0.031,"netbasalinsulin":-0.8,"hightempinsulin":0,"time":"2017-02-05T11:30:36.000Z"},{"iob":-0.022,"activity":-0.0018,"bolussnooze":0,"basaliob":-0.022,"netbasalinsulin":-0.75,"hightempinsulin":0,"time":"2017-02-05T11:35:36.000Z"},{"iob":-0.015,"activity":-0.0014,"bolussnooze":0,"basaliob":-0.015,"netbasalinsulin":-0.65,"hightempinsulin":0,"time":"2017-02-05T11:40:36.000Z"},{"iob":-0.01,"activity":-0.0011,"bolussnooze":0,"basaliob":-0.01,"netbasalinsulin":-0.55,"hightempinsulin":0,"time":"2017-02-05T11:45:36.000Z"},{"iob":-0.006,"activity":-0.0008,"bolussnooze":0,"basaliob":-0.006,"netbasalinsulin":-0.5,"hightempinsulin":0,"time":"2017-02-05T11:50:36.000Z"},{"iob":-0.003,"activity":-0.0006,"bolussnooze":0,"basaliob":-0.003,"netbasalinsulin":-0.4,"hightempinsulin":0,"time":"2017-02-05T11:55:36.000Z"},{"iob":-0.002,"activity":-0.0004,"bolussnooze":0,"basaliob":-0.002,"netbasalinsulin":-0.35,"hightempinsulin":0,"time":"2017-02-05T12:00:36.000Z"},{"iob":-0.001,"activity":-0.0002,"bolussnooze":0,"basaliob":-0.001,"netbasalinsulin":-0.25,"hightempinsulin":0,"time":"2017-02-05T12:05:36.000Z"},{"iob":0,"activity":-0.0001,"bolussnooze":0,"basaliob":0,"netbasalinsulin":-0.15,"hightempinsulin":0,"time":"2017-02-05T12:10:36.000Z"},{"iob":0,"activity":0,"bolussnooze":0,"basaliob":0,"netbasalinsulin":-0.1,"hightempinsulin":0,"time":"2017-02-05T12:15:36.000Z"},{"iob":0,"activity":0,"bolussnooze":0,"basaliob":0,"netbasalinsulin":0,"hightempinsulin":0,"time":"2017-02-05T12:20:36.000Z"},{"iob":0,"activity":0,"bolussnooze":0,"basaliob":0,"netbasalinsulin":0,"hightempinsulin":0,"time":"2017-02-05T12:25:36.000Z"}]
