[{"iob":-0.427,"activity":-0.005,"bolussnooze":0,"basaliob":-0.427,"netbasalinsulin":-0.85,"hightempinsulin":0,"time":"2016-10-08T12:26:27.000Z"},{"iob":-0.401,"activity":-0.0051,"bolussnooze":0,"basaliob":-0.401,"netbasalinsulin":-0.85,"hightempinsulin":0,"time":"2016-10-08T12:31:27.000Z"},{"iob":-0.375,"activity":-0.0052,"bolussnooze":0,"basaliob":-0.375,"netbasalinsulin":-0.85,"hightempinsulin":0,"time":"2016-10-08T12:36:27.000Z"},{"iob":-0.349,"activity":-0.0052,"bolussnooze":0,"basaliob":-0.349,"netbasalinsulin":-0.8,"hightempinsulin":0,"time":"2016-10-08T12:41:27.000Z"},{"iob":-0.323,"activity":-0.0052,"bolussnooze":0,"basaliob":-0.323,"netbasalinsulin":-0.8,"hightempinsulin":0,"time":"2016-10-08T12:46:27.000Z"},{"iob":-0.298,"activity":-0.0051,"bolussnooze":0,"basaliob":-0.298,"netbasalinsulin":-0.75,"hightempinsulin":0,"time":"2016-10-08T12:51:27.000Z"},{"iob":-0.272,"activity":-0.0051,"bolussnooze":0,"basaliob":-0.272,"netbasalinsulin":-0.7,"hightempinsulin":0,"time":"2016-10-08T12:56:27.000Z"},{"iob":-0.247,"activity":-0.005,"bolussnooze":0,"basaliob":-0.247,"netbasalinsulin":-0.65,"hightempinsulin":0,"time":"2016-10-08T13:01:27.000Z"},{"iob":-0.223,"activity":-0.0048,"bolussnooze":0,"basaliob":-0.223,"netbasalinsulin":-0.6,"hightempinsulin":0,"time":"2016-10-08T13:06:27.000Z"},{"iob":-0.2,"activity":-0.0047,"bolussnooze":0,"basaliob":-0.2,"netbasalinsulin":-0.55,"hightempinsulin":0,"time":"2016-10-08T13:11:27.000Z"},{"iob":-0.178,"activity":-0.0045,"bolussnooze":0,"basaliob":-0.178,"netbasalinsulin":-0.55,"hightempinsulin":0,"time":"2016-10-08T13:16:27.000Z"},{"iob":-0.156,"activity":-0.0042,"bolussnooze":0,"basaliob":-0.156,"netbasalinsulin":-0.55,"hightempinsulin":0,"time":"2016-10-08T13:21:27.000Z"},{"iob":-0.137,"activity":-0.004,"bolussnooze":0,"basaliob":-0.137,"netbasalinsulin":-0.55,"hightempinsulin":0,"time":"2016-10-08T13:26:27.000Z"},{"iob":-0.118,"activity":-0.0037,"bolussnooze":0,"basaliob":-0.118,"netbasalinsulin":-0.55,"hightempinsulin":0,"time":"2016-10-08T13:31:27.000Z"},{"iob":-0.101,"activity":-0.0034,"bolussnooze":0,"basaliob":-0.101,"netbasalinsulin":-0.55,"hightempinsulin":0,"time":"2016-10-08T13:36:27.000Z"},{"iob":-0.086,"activity":-0.0031,"bolussnooze":0,"basaliob":-0.086,"netbasalinsulin":-0.55,"hightempinsulin":0,"time":"2016-10-08T13:41:27.000Z"},{"iob":-0.072,"activity":-0.0028,"bolussnooze":0,"basaliob":-0.072,"netbasalinsulin":-0.55,"hightempinsulin":0,"time":"2016-10-08T13:46:27.000Z"},{"iob":-0.059,"activity":-0.0025,"bolussnooze":0,"basaliob":-0.059,"netbasalinsulin":-0.55,"hightempinsulin":0,"time":"2016-10-08T13:51:27.000Z"},{"iob":-0.048,"activity":-0.0022,"bolussnooze":0,"basaliob":-0.048,"netbasalinsulin":-0.55,"hightempinsulin":0,"time":"2016-10-08T13:56:27.000Z"},{"iob":-0.039,"activity":-0.0019,"bolussnooze":0,"basaliob":-0.039,"netbasalinsulin":-0.55,"hightempinsulin":0,"time":"2016-10-08T14:01:27.000Z"},{"iob":-0.03,"activity":-0.0017,"bolussnooze":0,"basaliob":-0.03,"netbasalinsulin":-0.5,"hightempinsulin":0,"time":"2016-10-08T14:06:27.000Z"},{"iob":-0.023,"activity":-0.0014,"bolussnooze":0,"basaliob":-0.023,"netbasalinsulin":-0.45,"hightempinsulin":0,"time":"2016-10-08T14:11:27.000Z"},{"iob":-0.018,"activity":-0.0012,"bolussnooze":0,"basaliob":-0.018,"netbasalinsulin":-0.4,"hightempinsulin":0,"time":"2016-10-08T14:16:27.000Z"},{"iob":-0.013,"activity":-0.001,"bolussnooze":0,"basaliob":-0.013,"netbasalinsulin":-0.4,"hightempinsulin":0,"time":"2016-10-08T14:21:27.000Z"},{"iob":-0.009,"activity":-0.0008,"bolussnooze":0,"basaliob":-0.009,"netbasalinsulin":-0.35,"hightempinsulin":0,"time":"2016-10-08T14:26:27.000Z"},{"iob":-0.006,"activity":-0.0006,"bolussnooze":0,"basaliob":-0.006,"netbasalinsulin":-0.3,"hightempinsulin":0,"time":"2016-10-08T14:31:27.000Z"},{"iob":-0.004,"activity":-0.0004,"bolussnooze":0,"basaliob":-0.004,"netbasalinsulin":-0.25,"hightempinsulin":0,"time":"2016-10-08T14:36:27.000Z"},{"iob":-0.002,"activity":-0.0003,"bolussnooze":0,"basaliob":-0.002,"netbasalinsulin":-0.2,"hightempinsulin":0,"time":"2016-10-08T14:41:27.000Z"},{"iob":-0.001,"activity":-0.0002,"bolussnooze":0,"basaliob":-0.001,"netbasalinsulin":-0.2,"hightempinsulin":0,"time":"2016-10-08T14:46:27.000Z"},{"iob":0,"activity":-0.0001,"bolussnooze":0,"basaliob":0,"netbasalinsulin":-0.15,"hightempinsulin":0,"time":"2016-10-08T14:51:27.000Z"},{"iob":0,"activity":-0.0001,"bolussnooze":0,"basaliob":0,"netbasalinsulin":-0.1,"hightempinsulin":0,"time":"2016-10-08T14:56:27.000Z"},{"iob":0,"activity":0,"bolussnooze":0,"basaliob":0,"netbasalinsulin":-0.05,"hightempinsulin":0,"time":"2016-10-08T15:01:27.000Z"},{"iob":0,"activity":0,"bolussnooze":0,"basaliob":0,"netbasalinsulin":-0.05,"hightempinsulin":0,"time":"2016-10-08T15:06:27.000Z"},{"iob":0,"activity":0,"bolussnooze":0,"basaliob":0,"netbasalinsulin":0,"hightempinsulin":0,"time":"2016-10-08T15:11:27.000Z"},{"iob":0,"activity":0,"bolussnooze":0,"basaliob":0,"netbasalinsulin":0,"hightempinsulin":0,"time":"2016-10-08T15:16:27.000Z"},{"iob":0,"activity":0,"bolussnooze":0,"basaliob":0,"netbasalinsulin":0,"hightempinsulin":0,"time":"2016-10-08T15:21:27.000Z"},{"iob":0,"activity":0,"bolussnooze":0,"basaliob":0,"netbasalinsulin":0,"hightempinsulin":0,"time":"2016-10-08T15:26:27.000Z"},{"iob":0,"activity":0,"bolussnooze":0,"basaliob":0,"netbasalinsulin":0,"hightempinsulin":0,"time":"2016-10-08T15:31:27.000Z"},{"iob":0,"activity":0,"bolussnooze":0,"basaliob":0,"netbasalinsulin":0,"hightempinsulin":0,"time":"2016-10-08T15:36:27.000Z"},{"iob":0,"activity":0,"bolussnooze":0,"basaliob":0,"netbasalinsulin":0,"hightempinsulin":0,"time":"2016-10-08T15:41:27.000Z"},{"iob":0,"activity":0,"bolussnooze":0,"basaliob":0,"netbasalinsulin":0,"hightempinsulin":0,"time":"2016-10-08T15:46:27.000Z"},{"iob":0,"activity":0,"bolussnooze":0,"basaliob":0,"netbasalinsulin":0,"hightempinsulin":0,"time":"2016-10-08T15:51:27.000Z"}]
