[{"iob":0.22,"activity":0.018,"bolussnooze":0,"basaliob":-0.332,"netbasalinsulin":0.85,"hightempinsulin":1.7,"time":"2016-09-15T04:27:20.000Z"},{"iob":0.14,"activity":0.016,"bolussnooze":0,"basaliob":-0.352,"netbasalinsulin":0.85,"hightempinsulin":1.7,"time":"2016-09-15T04:32:20.000Z"},{"iob":0.069,"activity":0.014,"bolussnooze":0,"basaliob":-0.366,"netbasalinsulin":0.9,"hightempinsulin":1.7,"time":"2016-09-15T04:37:20.000Z"},{"iob":0.009,"activity":0.0121,"bolussnooze":0,"basaliob":-0.373,"netbasalinsulin":0.95,"hightempinsulin":1.7,"time":"2016-09-15T04:42:20.000Z"},{"iob":-0.042,"activity":0.0102,"bolussnooze":0,"basaliob":-0.375,"netbasalinsulin":0.9,"hightempinsulin":1.65,"time":"2016-09-15T04:47:20.000Z"},{"iob":-0.084,"activity":0.0084,"bolussnooze":0,"basaliob":-0.37,"netbasalinsulin":0.8,"hightempinsulin":1.55,"time":"2016-09-15T04:52:20.000Z"},{"iob":-0.118,"activity":0.0068,"bolussnooze":0,"basaliob":-0.361,"netbasalinsulin":0.7,"hightempinsulin":1.45,"time":"2016-09-15T04:57:20.000Z"},{"iob":-0.144,"activity":0.0052,"bolussnooze":0,"basaliob":-0.348,"netbasalinsulin":0.6,"hightempinsulin":1.35,"time":"2016-09-15T05:02:20.000Z"},{"iob":-0.163,"activity":0.0038,"bolussnooze":0,"basaliob":-0.331,"netbasalinsulin":0.5,"hightempinsulin":1.25,"time":"2016-09-15T05:07:20.000Z"},{"iob":-0.175,"activity":0.0025,"bolussnooze":0,"basaliob":-0.312,"netbasalinsulin":0.4,"hightempinsulin":1.15,"time":"2016-09-15T05:12:20.000Z"},{"iob":-0.182,"activity":0.0013,"bolussnooze":0,"basaliob":-0.289,"netbasalinsulin":0.4,"hightempinsulin":1.15,"time":"2016-09-15T05:17:20.000Z"},{"iob":-0.183,"activity":0.0002,"bolussnooze":0,"basaliob":-0.265,"netbasalinsulin":0.25,"hightempinsulin":1,"time":"2016-09-15T05:22:20.000Z"},{"iob":-0.179,"activity":-0.0007,"bolussnooze":0,"basaliob":-0.239,"netbasalinsulin":0.05,"hightempinsulin":0.8,"time":"2016-09-15T05:27:20.000Z"},{"iob":-0.172,"activity":-0.0014,"bolussnooze":0,"basaliob":-0.213,"netbasalinsulin":-0.15,"hightempinsulin":0.6,"time":"2016-09-15T05:32:20.000Z"},{"iob":-0.162,"activity":-0.002,"bolussnooze":0,"basaliob":-0.188,"netbasalinsulin":-0.3,"hightempinsulin":0.45,"time":"2016-09-15T05:37:20.000Z"},{"iob":-0.149,"activity":-0.0025,"bolussnooze":0,"basaliob":-0.164,"netbasalinsulin":-0.5,"hightempinsulin":0.25,"time":"2016-09-15T05:42:20.000Z"},{"iob":-0.135,"activity":-0.0029,"bolussnooze":0,"basaliob":-0.141,"netbasalinsulin":-0.65,"hightempinsulin":0.1,"time":"2016-09-15T05:47:20.000Z"},{"iob":-0.119,"activity":-0.0032,"bolussnooze":0,"basaliob":-0.12,"netbasalinsulin":-0.75,"hightempinsulin":0,"time":"2016-09-15T05:52:20.000Z"},{"iob":-0.101,"activity":-0.0035,"bolussnooze":0,"basaliob":-0.101,"netbasalinsulin":-0.75,"hightempinsulin":0,"time":"2016-09-15T05:57:20.000Z"},{"iob":-0.084,"activity":-0.0034,"bolussnooze":0,"basaliob":-0.084,"netbasalinsulin":-0.7,"hightempinsulin":0,"time":"2016-09-15T06:02:20.000Z"},{"iob":-0.069,"activity":-0.003,"bolussnooze":0,"basaliob":-0.069,"netbasalinsulin":-0.65,"hightempinsulin":0,"time":"2016-09-15T06:07:20.000Z"},{"iob":-0.056,"activity":-0.0027,"bolussnooze":0,"basaliob":-0.056,"netbasalinsulin":-0.65,"hightempinsulin":0,"time":"2016-09-15T06:12:20.000Z"},{"iob":-0.044,"activity":-0.0023,"bolussnooze":0,"basaliob":-0.044,"netbasalinsulin":-0.65,"hightempinsulin":0,"time":"2016-09-15T06:17:20.000Z"},{"iob":-0.034,"activity":-0.002,"bolussnooze":0,"basaliob":-0.034,"netbasalinsulin":-0.65,"hightempinsulin":0,"time":"2016-09-15T06:22:20.000Z"},{"iob":-0.026,"activity":-0.0017,"bolussnooze":0,"basaliob":-0.026,"netbasalinsulin":-0.6,"hightempinsulin":0,"time":"2016-09-15T06:27:20.000Z"},{"iob":-0.019,"activity":-0.0014,"bolussnooze":0,"basaliob":-0.019,"netbasalinsulin":-0.55,"hightempinsulin":0,"time":"2016-09-15T06:32:20.000Z"},{"iob":-0.013,"activity":-0.0011,"bolussnooze":0,"basaliob":-0.013,"netbasalinsulin":-0.5,"hightempinsulin":0,"time":"2016-09-15T06:37:20.000Z"},{"iob":-0.009,"activity":-0.0009,"bolussnooze":0,"basaliob":-0.009,"netbasalinsulin":-0.4,"hightempinsulin":0,"time":"2016-09-15T06:42:20.000Z"},{"iob":-0.006,"activity":-0.0006,"bolussnooze":0,"basaliob":-0.006,"netbasalinsulin":-0.35,"hightempinsulin":0,"time":"2016-09-15T06:47:20.000Z"},{"iob":-0.003,"activity":-0.0005,"bolussnooze":0,"basaliob":-0.003,"netbasalinsulin":-0.3,"hightempinsulin":0,"time":"2016-09-15T06:52:20.000Z"},{"iob":-0.002,"activity":-0.0003,"bolussnooze":0,"basaliob":-0.002,"netbasalinsulin":-0.25,"hightempinsulin":0,"time":"2016-09-15T06:57:20.000Z"},{"iob":-0.001,"activity":-0.0002,"bolussnooze":0,"basaliob":-0.001,"netbasalinsulin":-0.2,"hightempinsulin":0,"time":"2016-09-15T07:02:20.000Z"},{"iob":0,"activity":-0.0001,"bolussnooze":0,"basaliob":0,"netbasalinsulin":-0.15,"hightempinsulin":0,"time":"2016-09-15T07:07:20.000Z"},{"iob":0,"activity":0,"bolussnooze":0,"basaliob":0,"netbasalinsulin":-0.1,"hightempinsulin":0,"time":"2016-09-15T07:12:20.000Z"},{"iob":0,"activity":0,"bolussnooze":0,"basaliob":0,"netbasalinsulin":-0.05,"hightempinsulin":0,"time":"2016-09-15T07:17:20.000Z"},{"iob":0,"activity":0,"bolussnooze":0,"basaliob":0,"netbasalinsulin":0,"hightempinsulin":0,"time":"2016-09-15T07:22:20.000Z"},{"iob":0,"activity":0,"bolussnooze":0,"basaliob":0,"netbasalinsulin":0,"hightempinsulin":0,"time":"2016-09-15T07:27:20.000Z"},{"iob":0,"activity":0,"bolussnooze":0,"basaliob":0,"netbasalinsulin":0,"hightempinsulin":0,"time":"2016-09-15T07:32:20.000Z"},{"iob":0,"activity":0,"bolussnooze":0,"basaliob":0,"netbasalinsulin":0,"hightempinsulin":0,"time":"2016-09-15T07:37:20.000Z"},{"iob":0,"activity":0,"bolussnooze":0,"basaliob":0,"netbasalinsulin":0,"hightempinsulin":0,"time":"2016-09-15T07:42:20.000Z"},{"iob":0,"activity":0,"bolussnooze":0,"basaliob":0,"netbasalinsulin":0,"hightempinsulin":0,"time":"2016-09-15T07:47:20.000Z"},{"iob":0,"activity":0,"bolussnooze":0,"basaliob":0,"netbasalinsulin":0,"hightempinsulin":0,"time":"2016-09-15T07:52:20.000Z"}]
