{
  "requested": {
    "duration": 30, 
    "rate": 2.25, 
    "temp": "absolute"
  }, 
  "bg": 119, 
  "temp": "absolute", 
  "snoozeBG": 221, 
  "timestamp": "2016-06-13T22:04:21.717751", 
  "predBGs": {
    "IOB": [
      119, 
      130, 
      141, 
      151, 
      160, 
      169, 
      178, 
      185, 
      192, 
      197, 
      201, 
      205, 
      207, 
      208, 
      210, 
      211, 
      213, 
      214, 
      215, 
      215, 
      216, 
      216, 
      217, 
      217, 
      217, 
      217, 
      218
    ]
  }, 
  "rate": 0.8, 
  "reason": "COB: 0, Dev: 63, BGI: 1.48, ISF: 72.1, Target: 110; Eventual BG 221>=110, adj. req. rate:3.9 to maxSafeBasal:2.3, temp 0.8<2.3U/hr", 
  "COB": 0, 
  "eventualBG": 221, 
  "recieved": false, 
  "duration": 2, 
  "tick": "+12", 
  "IOB": -0.547
}