{
  "bg": 101, 
  "temp": "absolute", 
  "snoozeBG": 132, 
  "recieved": true, 
  "predBGs": {
    "IOB": [
      101, 
      100, 
      99, 
      98, 
      99, 
      99, 
      100, 
      101, 
      102, 
      104, 
      106, 
      107, 
      109, 
      110, 
      112, 
      113, 
      115, 
      116, 
      118, 
      119, 
      120, 
      121, 
      122, 
      123, 
      123, 
      124, 
      124, 
      125
    ]
  }, 
  "rate": 0.2, 
  "reason": "COB: 0, Dev: 28, BGI: -5.65, ISF: 127, Target: 147; Eventual BG 132<147, Snooze BG 132, setting 0.22U/hr", 
  "COB": 0, 
  "eventualBG": 132, 
  "timestamp": "2016-06-12T00:27:44.307693", 
  "duration": 30, 
  "tick": -1, 
  "IOB": -0.032
}