{
  "bg": 180, 
  "temp": "absolute", 
  "snoozeBG": 125, 
  "recieved": true, 
  "predBGs": {
    "IOB": [
      180, 
      178, 
      176, 
      173, 
      171, 
      168, 
      165, 
      162, 
      159, 
      155, 
      152, 
      148, 
      145, 
      141, 
      138, 
      134, 
      131, 
      128, 
      125, 
      122, 
      120, 
      118, 
      116, 
      114, 
      112, 
      111, 
      109, 
      108, 
      107, 
      106, 
      106, 
      105, 
      104, 
      104, 
      104, 
      104, 
      103
    ]
  }, 
  "rate": 0.45, 
  "reason": "COB: 0, Dev: 3, BGI: -1.5, ISF: 94, Target: 117; Eventual BG 125 > 117 but Min. Delta -2.00 < Exp. Delta -1.9; setting current basal of 0.475 as temp", 
  "COB": 0, 
  "eventualBG": 125, 
  "timestamp": "2016-09-26T05:57:53.112648", 
  "duration": 30, 
  "tick": -2, 
  "IOB": 0.623
}