{
  "device": "openaps://indy-e4", 
  "pump": {
    "battery": {
      "status": "normal", 
      "voltage": 1.47
    }, 
    "status": {
      "status": "normal", 
      "timestamp": "2016-07-10T11:52:50.000Z", 
      "bolusing": false, 
      "suspended": false
    }, 
    "reservoir": 83.55, 
    "clock": "2016-07-10T04:52:30-07:00"
  }, 
  "openaps": {
    "suggested": {
      "bg": 151, 
      "temp": "absolute", 
      "snoozeBG": 124, 
      "timestamp": "2016-07-10T11:54:06.000Z", 
      "predBGs": {
        "IOB": [
          151, 
          149, 
          147, 
          145, 
          143, 
          141, 
          139, 
          137, 
          136, 
          134, 
          132, 
          131, 
          129, 
          128, 
          127, 
          126, 
          125, 
          124, 
          123, 
          122, 
          121, 
          120, 
          120, 
          119, 
          118, 
          118, 
          118, 
          117, 
          117, 
          117, 
          117, 
          117, 
          116
        ]
      }, 
      "reason": "COB: 0, Dev: 7, BGI: -3.2, ISF: 80, Target: 115; Eventual BG 124>=115, temp 0.55 >~ req 0.5U/hr", 
      "COB": 0, 
      "eventualBG": 124, 
      "tick": -1, 
      "IOB": 0.429
    }, 
    "iob": [
      {
        "netbasalinsulin": 1.4, 
        "activity": 0.008, 
        "basaliob": 0.429, 
        "time": "2016-07-10T11:52:30.000Z", 
        "hightempinsulin": 1.45, 
        "bolussnooze": 0, 
        "iob": 0.429
      }, 
      {
        "netbasalinsulin": 1.4, 
        "activity": 0.0077, 
        "basaliob": 0.391, 
        "time": "2016-07-10T11:57:30.000Z", 
        "hightempinsulin": 1.45, 
        "bolussnooze": 0, 
        "iob": 0.391
      }, 
      {
        "netbasalinsulin": 1.4, 
        "activity": 0.0073, 
        "basaliob": 0.355, 
        "time": "2016-07-10T12:02:30.000Z", 
        "hightempinsulin": 1.45, 
        "bolussnooze": 0, 
        "iob": 0.355
      }, 
      {
        "netbasalinsulin": 1.4, 
        "activity": 0.0069, 
        "basaliob": 0.37, 
        "time": "2016-07-10T12:07:30.000Z", 
        "hightempinsulin": 1.45, 
        "bolussnooze": 0, 
        "iob": 0.37
      }, 
      {
        "netbasalinsulin": 1.4, 
        "activity": 0.0065, 
        "basaliob": 0.337, 
        "time": "2016-07-10T12:12:30.000Z", 
        "hightempinsulin": 1.45, 
        "bolussnooze": 0, 
        "iob": 0.337
      }, 
      {
        "netbasalinsulin": 1.35, 
        "activity": 0.0061, 
        "basaliob": 0.307, 
        "time": "2016-07-10T12:17:30.000Z", 
        "hightempinsulin": 1.4, 
        "bolussnooze": 0, 
        "iob": 0.307
      }, 
      {
        "netbasalinsulin": 1.25, 
        "activity": 0.0057, 
        "basaliob": 0.279, 
        "time": "2016-07-10T12:22:30.000Z", 
        "hightempinsulin": 1.3, 
        "bolussnooze": 0, 
        "iob": 0.279
      }, 
      {
        "netbasalinsulin": 1.2, 
        "activity": 0.0052, 
        "basaliob": 0.252, 
        "time": "2016-07-10T12:27:30.000Z", 
        "hightempinsulin": 1.25, 
        "bolussnooze": 0, 
        "iob": 0.252
      }, 
      {
        "netbasalinsulin": 1.15, 
        "activity": 0.0048, 
        "basaliob": 0.228, 
        "time": "2016-07-10T12:32:30.000Z", 
        "hightempinsulin": 1.2, 
        "bolussnooze": 0, 
        "iob": 0.228
      }, 
      {
        "netbasalinsulin": 1.05, 
        "activity": 0.0044, 
        "basaliob": 0.206, 
        "time": "2016-07-10T12:37:30.000Z", 
        "hightempinsulin": 1.1, 
        "bolussnooze": 0, 
        "iob": 0.206
      }, 
      {
        "netbasalinsulin": 0.95, 
        "activity": 0.0041, 
        "basaliob": 0.186, 
        "time": "2016-07-10T12:42:30.000Z", 
        "hightempinsulin": 1, 
        "bolussnooze": 0, 
        "iob": 0.186
      }, 
      {
        "netbasalinsulin": 0.85, 
        "activity": 0.0037, 
        "basaliob": 0.168, 
        "time": "2016-07-10T12:47:30.000Z", 
        "hightempinsulin": 0.9, 
        "bolussnooze": 0, 
        "iob": 0.168
      }, 
      {
        "netbasalinsulin": 0.75, 
        "activity": 0.0034, 
        "basaliob": 0.151, 
        "time": "2016-07-10T12:52:30.000Z", 
        "hightempinsulin": 0.8, 
        "bolussnooze": 0, 
        "iob": 0.151
      }, 
      {
        "netbasalinsulin": 0.65, 
        "activity": 0.0031, 
        "basaliob": 0.135, 
        "time": "2016-07-10T12:57:30.000Z", 
        "hightempinsulin": 0.7, 
        "bolussnooze": 0, 
        "iob": 0.135
      }, 
      {
        "netbasalinsulin": 0.6, 
        "activity": 0.0029, 
        "basaliob": 0.12, 
        "time": "2016-07-10T13:02:30.000Z", 
        "hightempinsulin": 0.65, 
        "bolussnooze": 0, 
        "iob": 0.12
      }, 
      {
        "netbasalinsulin": 0.5, 
        "activity": 0.0028, 
        "basaliob": 0.107, 
        "time": "2016-07-10T13:07:30.000Z", 
        "hightempinsulin": 0.55, 
        "bolussnooze": 0, 
        "iob": 0.107
      }, 
      {
        "netbasalinsulin": 0.4, 
        "activity": 0.0026, 
        "basaliob": 0.094, 
        "time": "2016-07-10T13:12:30.000Z", 
        "hightempinsulin": 0.45, 
        "bolussnooze": 0, 
        "iob": 0.094
      }, 
      {
        "netbasalinsulin": 0.45, 
        "activity": 0.0024, 
        "basaliob": 0.082, 
        "time": "2016-07-10T13:17:30.000Z", 
        "hightempinsulin": 0.45, 
        "bolussnooze": 0, 
        "iob": 0.082
      }, 
      {
        "netbasalinsulin": 0.45, 
        "activity": 0.0022, 
        "basaliob": 0.07, 
        "time": "2016-07-10T13:22:30.000Z", 
        "hightempinsulin": 0.45, 
        "bolussnooze": 0, 
        "iob": 0.07
      }, 
      {
        "netbasalinsulin": 0.45, 
        "activity": 0.002, 
        "basaliob": 0.06, 
        "time": "2016-07-10T13:27:30.000Z", 
        "hightempinsulin": 0.45, 
        "bolussnooze": 0, 
        "iob": 0.06
      }, 
      {
        "netbasalinsulin": 0.4, 
        "activity": 0.0018, 
        "basaliob": 0.051, 
        "time": "2016-07-10T13:32:30.000Z", 
        "hightempinsulin": 0.4, 
        "bolussnooze": 0, 
        "iob": 0.051
      }, 
      {
        "netbasalinsulin": 0.4, 
        "activity": 0.0016, 
        "basaliob": 0.043, 
        "time": "2016-07-10T13:37:30.000Z", 
        "hightempinsulin": 0.4, 
        "bolussnooze": 0, 
        "iob": 0.043
      }, 
      {
        "netbasalinsulin": 0.35, 
        "activity": 0.0014, 
        "basaliob": 0.037, 
        "time": "2016-07-10T13:42:30.000Z", 
        "hightempinsulin": 0.35, 
        "bolussnooze": 0, 
        "iob": 0.037
      }, 
      {
        "netbasalinsulin": 0.3, 
        "activity": 0.0012, 
        "basaliob": 0.031, 
        "time": "2016-07-10T13:47:30.000Z", 
        "hightempinsulin": 0.3, 
        "bolussnooze": 0, 
        "iob": 0.031
      }, 
      {
        "netbasalinsulin": 0.3, 
        "activity": 0.001, 
        "basaliob": 0.025, 
        "time": "2016-07-10T13:52:30.000Z", 
        "hightempinsulin": 0.3, 
        "bolussnooze": 0, 
        "iob": 0.025
      }, 
      {
        "netbasalinsulin": 0.25, 
        "activity": 0.0009, 
        "basaliob": 0.021, 
        "time": "2016-07-10T13:57:30.000Z", 
        "hightempinsulin": 0.25, 
        "bolussnooze": 0, 
        "iob": 0.021
      }, 
      {
        "netbasalinsulin": 0.2, 
        "activity": 0.0008, 
        "basaliob": 0.017, 
        "time": "2016-07-10T14:02:30.000Z", 
        "hightempinsulin": 0.2, 
        "bolussnooze": 0, 
        "iob": 0.017
      }, 
      {
        "netbasalinsulin": 0.2, 
        "activity": 0.0007, 
        "basaliob": 0.014, 
        "time": "2016-07-10T14:07:30.000Z", 
        "hightempinsulin": 0.2, 
        "bolussnooze": 0, 
        "iob": 0.014
      }, 
      {
        "netbasalinsulin": 0.15, 
        "activity": 0.0006, 
        "basaliob": 0.011, 
        "time": "2016-07-10T14:12:30.000Z", 
        "hightempinsulin": 0.15, 
        "bolussnooze": 0, 
        "iob": 0.011
      }, 
      {
        "netbasalinsulin": 0.15, 
        "activity": 0.0005, 
        "basaliob": 0.008, 
        "time": "2016-07-10T14:17:30.000Z", 
        "hightempinsulin": 0.15, 
        "bolussnooze": 0, 
        "iob": 0.008
      }, 
      {
        "netbasalinsulin": 0.15, 
        "activity": 0.0004, 
        "basaliob": 0.006, 
        "time": "2016-07-10T14:22:30.000Z", 
        "hightempinsulin": 0.15, 
        "bolussnooze": 0, 
        "iob": 0.006
      }, 
      {
        "netbasalinsulin": 0.1, 
        "activity": 0.0003, 
        "basaliob": 0.005, 
        "time": "2016-07-10T14:27:30.000Z", 
        "hightempinsulin": 0.1, 
        "bolussnooze": 0, 
        "iob": 0.005
      }, 
      {
        "netbasalinsulin": 0.1, 
        "activity": 0.0003, 
        "basaliob": 0.003, 
        "time": "2016-07-10T14:32:30.000Z", 
        "hightempinsulin": 0.1, 
        "bolussnooze": 0, 
        "iob": 0.003
      }, 
      {
        "netbasalinsulin": 0.1, 
        "activity": 0.0002, 
        "basaliob": 0.002, 
        "time": "2016-07-10T14:37:30.000Z", 
        "hightempinsulin": 0.1, 
        "bolussnooze": 0, 
        "iob": 0.002
      }, 
      {
        "netbasalinsulin": 0.1, 
        "activity": 0.0002, 
        "basaliob": 0.001, 
        "time": "2016-07-10T14:42:30.000Z", 
        "hightempinsulin": 0.1, 
        "bolussnooze": 0, 
        "iob": 0.001
      }, 
      {
        "netbasalinsulin": 0.1, 
        "activity": 0.0001, 
        "basaliob": 0.001, 
        "time": "2016-07-10T14:47:30.000Z", 
        "hightempinsulin": 0.1, 
        "bolussnooze": 0, 
        "iob": 0.001
      }
    ]
  }, 
  "mmtune": {
    "scanDetails": [
      [
        "916.540", 
        5, 
        -81
      ], 
      [
        "916.564", 
        5, 
        -68
      ], 
      [
        "916.588", 
        5, 
        -66
      ], 
      [
        "916.612", 
        5, 
        -66
      ], 
      [
        "916.636", 
        5, 
        -66
      ], 
      [
        "916.660", 
        5, 
        -67
      ], 
      [
        "916.684", 
        5, 
        -71
      ]
    ], 
    "setFreq": 916.636, 
    "timestamp": "2016-07-10T11:52:30.000Z", 
    "usedDefault": false
  }
}