{
  "device": "openaps://indy-e4", 
  "pump": {
    "battery": {
      "status": "normal", 
      "voltage": 1.44
    }, 
    "status": {
      "status": "normal", 
      "timestamp": "2016-08-31T05:39:44.000Z", 
      "bolusing": false, 
      "suspended": false
    }, 
    "reservoir": 144.075, 
    "clock": "2016-08-30T22:39:42-07:00"
  }, 
  "openaps": {
    "suggested": {
      "bg": 52, 
      "temp": "absolute", 
      "snoozeBG": 123, 
      "timestamp": "2016-08-31T05:41:24.000Z", 
      "predBGs": {
        "COB": [
          52, 
          59, 
          66, 
          74, 
          82, 
          91, 
          99, 
          107, 
          115, 
          123, 
          132, 
          140, 
          148, 
          156, 
          164, 
          171, 
          179, 
          186, 
          193, 
          199, 
          205, 
          211, 
          217, 
          222, 
          227, 
          231, 
          236, 
          240, 
          244, 
          248, 
          251, 
          254, 
          257, 
          260, 
          263, 
          266, 
          268, 
          270, 
          273, 
          275, 
          277, 
          279, 
          281
        ], 
        "aCOB": [
          52, 
          65, 
          78, 
          91, 
          104, 
          117, 
          130, 
          142, 
          154, 
          166, 
          178, 
          189, 
          201, 
          211, 
          222, 
          232, 
          241, 
          250, 
          258, 
          266, 
          273, 
          280, 
          286, 
          292, 
          297, 
          301, 
          305, 
          309, 
          312, 
          314, 
          316, 
          318, 
          319, 
          320, 
          320, 
          320, 
          320, 
          321
        ], 
        "IOB": [
          52, 
          59, 
          66, 
          73, 
          80, 
          86, 
          93, 
          99, 
          105, 
          111, 
          116, 
          121, 
          126, 
          130, 
          135, 
          139, 
          143, 
          147, 
          151, 
          154, 
          157, 
          160, 
          163, 
          165, 
          167, 
          169, 
          170, 
          172, 
          173, 
          174, 
          175, 
          176, 
          176, 
          177, 
          177, 
          177, 
          177, 
          178
        ]
      }, 
      "reason": "COB: 34, Dev: -14, BGI: 3.01, ISF: 90, Target: 115; BG 52<83, but 30m left and 0 ~ req 0U/hr: no action required", 
      "COB": 34, 
      "eventualBG": 281, 
      "tick": "+10", 
      "IOB": -0.868
    }, 
    "iob": {
      "netbasalinsulin": -1.2, 
      "timestamp": "2016-08-31T05:39:42.000Z", 
      "activity": -0.0067, 
      "basaliob": -0.871, 
      "hightempinsulin": 0.1, 
      "bolussnooze": 0, 
      "iob": -0.868
    }, 
    "enacted": {
      "bg": 47, 
      "temp": "absolute", 
      "snoozeBG": 110, 
      "recieved": true, 
      "reason": "COB: 36, Dev: -19, BGI: 1.35, ISF: 90, Target: 115; BG 47<83", 
      "rate": 0, 
      "COB": 36, 
      "eventualBG": 262, 
      "timestamp": "2016-08-31T05:28:26.000Z", 
      "duration": 30, 
      "tick": -2, 
      "IOB": -0.747
    }
  }, 
  "mmtune": {
    "scanDetails": [
      [
        "916.540", 
        4, 
        -84
      ], 
      [
        "916.564", 
        5, 
        -73
      ], 
      [
        "916.588", 
        5, 
        -71
      ], 
      [
        "916.612", 
        5, 
        -70
      ], 
      [
        "916.636", 
        5, 
        -71
      ], 
      [
        "916.660", 
        5, 
        -72
      ], 
      [
        "916.684", 
        5, 
        -75
      ]
    ], 
    "setFreq": 916.612, 
    "timestamp": "2016-08-31T05:39:24.000Z", 
    "usedDefault": false
  }
}